pyrasite/__init__.py
pyrasite/injector.py
pyrasite/inspector.py
pyrasite/ipc.py
pyrasite/main.py
pyrasite/reverse.py
pyrasite/payloads/__init__.py
pyrasite/payloads/dump_memory.py
pyrasite/payloads/dump_modules.py
pyrasite/payloads/dump_stacks.py
pyrasite/payloads/force_garbage_collection.py
pyrasite/payloads/helloworld.py
pyrasite/payloads/reverse_python_shell.py
pyrasite/payloads/reverse_shell.py
pyrasite/payloads/start_callgraph.py
pyrasite/payloads/stop_callgraph.py
pyrasite/tests/__init__.py
pyrasite/tests/context_manager_case.py
pyrasite/tests/test_cli.py
pyrasite/tests/test_code_injection.py
pyrasite/tests/test_ipc.py
pyrasite/tests/utils.py
pyrasite/tools/__init__.py
pyrasite/tools/memory_viewer.py
pyrasite/tools/shell.py
pyrasite_ng-2.0.3.dist-info/LICENSE
pyrasite_ng-2.0.3.dist-info/METADATA
pyrasite_ng-2.0.3.dist-info/WHEEL
pyrasite_ng-2.0.3.dist-info/entry_points.txt
pyrasite_ng-2.0.3.dist-info/top_level.txt
pyrasite_ng-2.0.3.dist-info/RECORD
