Metadata-Version: 2.2
Name: pyrasite-ng
Version: 2.0.3
Summary: Inject code into a running Python process
Home-page: https://github.com/user202729/pyrasite-ng
Author: Luke Macken
Author-email: lmacken@redhat.com
License: GPLv3
Keywords: debugging injection runtime
Classifier: Development Status :: 4 - Beta
Classifier: Environment :: Console
Classifier: Intended Audience :: Developers
Classifier: Intended Audience :: System Administrators
Classifier: License :: OSI Approved :: GNU General Public License (GPL)
Classifier: Topic :: System :: Monitoring
Classifier: Topic :: Software Development :: Debuggers
Classifier: Programming Language :: Python
Classifier: Programming Language :: Python :: 3
License-File: LICENSE
Requires-Dist: urwid
Dynamic: author
Dynamic: author-email
Dynamic: classifier
Dynamic: description
Dynamic: home-page
Dynamic: keywords
Dynamic: license
Dynamic: requires-dist
Dynamic: summary
